uarttool/__init__.py
uarttool/main.py
uart_tool-0.0.4.dist-info/METADATA
uart_tool-0.0.4.dist-info/WHEEL
uart_tool-0.0.4.dist-info/entry_points.txt
uart_tool-0.0.4.dist-info/top_level.txt
uart_tool-0.0.4.dist-info/RECORD
