Metadata-Version: 2.1
Name: uart-tool
Version: 0.0.4
Summary: uart 工具
Author: nobitaqaq
Author-email: xiaoleigs@gmail.com
Keywords: uart,uart-tool
Requires-Python: >=3.8
Requires-Dist: pyserial
Requires-Dist: colorama
